MANIFEST.in
README.rst
VERSION
setup.py
xanadu/__init__.py
xanadu/const.py
xanadu/errors.py
xanadu/request.py
xanadu/response.py
xanadu/temp.py
xanadu/util.py
xanadu/xanadu.py
xanadu.egg-info/PKG-INFO
xanadu.egg-info/SOURCES.txt
xanadu.egg-info/dependency_links.txt
xanadu.egg-info/top_level.txt