Metadata-Version: 1.1
Name: xanadu
Version: 0.0.21
Summary: xanadu: a new web framework. - by xlzd
Home-page: https://github.com/xlzd/xanadu
Author: xlzd
Author-email: i@xlzd.me
License: GPLv2
Download-URL: https://github.com/xlzd/xanadu
Keywords: xlzd,xanadu,webframework
Platform: UNKNOWN
Classifier: Environment :: Web Environment
Classifier: Intended Audience :: Developers
Classifier: Operating System :: OS Independent
Classifier: Programming Language :: Python :: 2
Classifier: Topic :: Internet :: WWW/HTTP
Classifier: Topic :: Software Development :: Libraries :: Python Modules
